LICENSE
README.md
setup.py
start_zero.egg-info/PKG-INFO
start_zero.egg-info/SOURCES.txt
start_zero.egg-info/dependency_links.txt
start_zero.egg-info/top_level.txt
test/test_math_ops.py
test/test_model_grad.py
test/test_model_mnist.py
test/test_transformer_load.py
test/test_transformer_test.py
test/test_transformer_train.py
zero/__init__.py
zero/accelerate/__init__.py
zero/accelerate/cupy.py
zero/core/__init__.py
zero/core/layer.py
zero/core/model.py
zero/core/optimizer.py
zero/core/tensor.py
zero/ds/__init__.py
zero/ds/queue.py
zero/ds/stack.py
zero/layers/__init__.py
zero/layers/linear.py
zero/layers/ne.py
zero/layers/ted.py
zero/models/__init__.py
zero/models/mlp.py
zero/models/transformer.py
zero/ops/__init__.py
zero/ops/act_ops.py
zero/ops/base_op.py
zero/ops/compare_ops.py
zero/ops/exp_log_ops.py
zero/ops/linear_ops.py
zero/ops/loss_ops.py
zero/ops/math_ops.py
zero/ops/norm_ops.py
zero/ops/tri_ops.py
zero/ops/util_ops.py
zero/optimizers/__init__.py
zero/optimizers/sgd.py
zero/utils/__init__.py
zero/utils/math.py
zero/utils/perf.py
zero/utils/vocab.py