Metadata-Version: 2.4
Name: start-zero
Version: 0.2.1
Summary: 深度学习框架（Deep Learning Framework）
Home-page: https://gitee.com/tank2140896/start-zero
Author: HeBin
Author-email: hebingaa@126.com
License: Apache License 2.0
Classifier: Intended Audience :: Developers
Classifier: Operating System :: OS Independent
Classifier: Natural Language :: Chinese (Simplified)
Classifier: Natural Language :: Chinese (Traditional)
Classifier: Natural Language :: English
Classifier: Programming Language :: Python :: 3.12
License-File: LICENSE
Dynamic: author
Dynamic: author-email
Dynamic: classifier
Dynamic: description
Dynamic: description-content-type
Dynamic: home-page
Dynamic: license
Dynamic: license-file
Dynamic: summary
